secops/__init__.py
secops/auth.py
secops/client.py
secops/exceptions.py
secops/chronicle/__init__.py
secops/chronicle/alert.py
secops/chronicle/case.py
secops/chronicle/client.py
secops/chronicle/dashboard.py
secops/chronicle/dashboard_query.py
secops/chronicle/data_export.py
secops/chronicle/data_table.py
secops/chronicle/entity.py
secops/chronicle/featured_content_rules.py
secops/chronicle/feeds.py
secops/chronicle/gemini.py
secops/chronicle/ioc.py
secops/chronicle/log_ingest.py
secops/chronicle/log_processing_pipelines.py
secops/chronicle/log_types.py
secops/chronicle/models.py
secops/chronicle/nl_search.py
secops/chronicle/parser.py
secops/chronicle/parser_extension.py
secops/chronicle/reference_list.py
secops/chronicle/rule.py
secops/chronicle/rule_alert.py
secops/chronicle/rule_detection.py
secops/chronicle/rule_exclusion.py
secops/chronicle/rule_retrohunt.py
secops/chronicle/rule_set.py
secops/chronicle/rule_validation.py
secops/chronicle/search.py
secops/chronicle/stats.py
secops/chronicle/udm_mapping.py
secops/chronicle/udm_search.py
secops/chronicle/validate.py
secops/chronicle/watchlist.py
secops/chronicle/utils/__init__.py
secops/chronicle/utils/request_utils.py
secops/cli/__init__.py
secops/cli/cli_client.py
secops/cli/constants.py
secops/cli/commands/alert.py
secops/cli/commands/case.py
secops/cli/commands/config.py
secops/cli/commands/curated_rule.py
secops/cli/commands/dashboard.py
secops/cli/commands/dashboard_query.py
secops/cli/commands/data_table.py
secops/cli/commands/entity.py
secops/cli/commands/export.py
secops/cli/commands/featured_content_rules.py
secops/cli/commands/feed.py
secops/cli/commands/forwarder.py
secops/cli/commands/gemini.py
secops/cli/commands/help.py
secops/cli/commands/iocs.py
secops/cli/commands/log.py
secops/cli/commands/log_processing.py
secops/cli/commands/parser.py
secops/cli/commands/parser_extension.py
secops/cli/commands/reference_list.py
secops/cli/commands/rule.py
secops/cli/commands/rule_exclusion.py
secops-0.31.0.dist-info/METADATA
secops-0.31.0.dist-info/WHEEL
secops-0.31.0.dist-info/entry_points.txt
secops-0.31.0.dist-info/licenses/LICENSE
secops-0.31.0.dist-info/RECORD
