Metadata-Version: 2.4
Name: secops
Version: 0.31.0
Summary: Python SDK for wrapping the Google SecOps API for common use cases
Project-URL: Homepage, https://github.com/google/secops-wrapper
Project-URL: Documentation, https://github.com/google/secops-wrapper#readme
Project-URL: Repository, https://github.com/google/secops-wrapper.git
Project-URL: Issues, https://github.com/google/secops-wrapper/issues
Author-email: Google SecOps Team <chronicle@google.com>
License-Expression: Apache-2.0
License-File: LICENSE
Keywords: chronicle,google,secops,security
Classifier: Development Status :: 3 - Alpha
Classifier: Intended Audience :: Developers
Classifier: License :: OSI Approved :: Apache Software License
Classifier: Programming Language :: Python :: 3
Classifier: Programming Language :: Python :: 3.10
Classifier: Programming Language :: Python :: 3.11
Classifier: Programming Language :: Python :: 3.12
Classifier: Programming Language :: Python :: 3.13
Classifier: Topic :: Security
Requires-Python: >=3.10
Requires-Dist: google-api-python-client>=2.0.0
Requires-Dist: google-auth-httplib2>=0.1.0
Requires-Dist: google-auth>=2.0.0
Provides-Extra: docs
Requires-Dist: sphinx-rtd-theme>=1.0.0; extra == 'docs'
Requires-Dist: sphinx>=4.0.0; extra == 'docs'
Provides-Extra: test
Requires-Dist: pytest-cov>=3.0.0; extra == 'test'
Requires-Dist: pytest>=7.0.0; extra == 'test'
Requires-Dist: python-dotenv>=0.17.1; extra == 'test'
Requires-Dist: tox>=3.24.0; extra == 'test'
